{
	"configurations" : 
	[
		{
			"directories" : 
			[
				{
					"build" : ".",
					"hasInstallRule" : true,
					"jsonFile" : "directory-.-Debug-1e61e72af30e6c2aedc3.json",
					"minimumCMakeVersion" : 
					{
						"string" : "3.12"
					},
					"projectIndex" : 0,
					"source" : ".",
					"targetIndexes" : 
					[
						0,
						1,
						2,
						3
					]
				}
			],
			"name" : "Debug",
			"projects" : 
			[
				{
					"directoryIndexes" : 
					[
						0
					],
					"name" : "rosidl_cmake",
					"targetIndexes" : 
					[
						0,
						1,
						2,
						3
					]
				}
			],
			"targets" : 
			[
				{
					"directoryIndex" : 0,
					"id" : "ament_cmake_python_build_rosidl_cmake_egg::@6890427a1f51a3e7e1df",
					"jsonFile" : "target-ament_cmake_python_build_rosidl_cmake_egg-Debug-33a34294e236b61707ca.json",
					"name" : "ament_cmake_python_build_rosidl_cmake_egg",
					"projectIndex" : 0
				},
				{
					"directoryIndex" : 0,
					"id" : "ament_cmake_python_copy_rosidl_cmake::@6890427a1f51a3e7e1df",
					"jsonFile" : "target-ament_cmake_python_copy_rosidl_cmake-Debug-1be926307372249133b4.json",
					"name" : "ament_cmake_python_copy_rosidl_cmake",
					"projectIndex" : 0
				},
				{
					"directoryIndex" : 0,
					"id" : "rosidl_cmake_uninstall::@6890427a1f51a3e7e1df",
					"jsonFile" : "target-rosidl_cmake_uninstall-Debug-6289207c0c81625ee90c.json",
					"name" : "rosidl_cmake_uninstall",
					"projectIndex" : 0
				},
				{
					"directoryIndex" : 0,
					"id" : "uninstall::@6890427a1f51a3e7e1df",
					"jsonFile" : "target-uninstall-Debug-10b8b0127ede56c8505f.json",
					"name" : "uninstall",
					"projectIndex" : 0
				}
			]
		}
	],
	"kind" : "codemodel",
	"paths" : 
	{
		"build" : "/home/agustin/STM32CubeIDE/workspace_1.19.0/testURosSetup/uros_ws/firmware/mcu_ws/build/rosidl_cmake",
		"source" : "/home/agustin/STM32CubeIDE/workspace_1.19.0/testURosSetup/uros_ws/firmware/mcu_ws/ros2/rosidl/rosidl_cmake"
	},
	"version" : 
	{
		"major" : 2,
		"minor" : 3
	}
}
